huaweicloudsdkorganizations/__init__.py
huaweicloudsdkorganizations/v1/__init__.py
huaweicloudsdkorganizations/v1/organizations_async_client.py
huaweicloudsdkorganizations/v1/organizations_client.py
huaweicloudsdkorganizations/v1/model/__init__.py
huaweicloudsdkorganizations/v1/model/accept_handshake_request.py
huaweicloudsdkorganizations/v1/model/accept_handshake_response.py
huaweicloudsdkorganizations/v1/model/account_dto.py
huaweicloudsdkorganizations/v1/model/attach_policy_request.py
huaweicloudsdkorganizations/v1/model/attach_policy_response.py
huaweicloudsdkorganizations/v1/model/cancel_handshake_request.py
huaweicloudsdkorganizations/v1/model/cancel_handshake_response.py
huaweicloudsdkorganizations/v1/model/close_account_request.py
huaweicloudsdkorganizations/v1/model/close_account_response.py
huaweicloudsdkorganizations/v1/model/close_account_status_dto.py
huaweicloudsdkorganizations/v1/model/create_account_req_body.py
huaweicloudsdkorganizations/v1/model/create_account_request.py
huaweicloudsdkorganizations/v1/model/create_account_response.py
huaweicloudsdkorganizations/v1/model/create_account_status_dto.py
huaweicloudsdkorganizations/v1/model/create_account_status_dto_failure_detail_msg.py
huaweicloudsdkorganizations/v1/model/create_organization_request.py
huaweicloudsdkorganizations/v1/model/create_organization_response.py
huaweicloudsdkorganizations/v1/model/create_organizational_unit_req_body.py
huaweicloudsdkorganizations/v1/model/create_organizational_unit_request.py
huaweicloudsdkorganizations/v1/model/create_organizational_unit_response.py
huaweicloudsdkorganizations/v1/model/create_policy_req_body.py
huaweicloudsdkorganizations/v1/model/create_policy_request.py
huaweicloudsdkorganizations/v1/model/create_policy_response.py
huaweicloudsdkorganizations/v1/model/create_resource_account_req_body.py
huaweicloudsdkorganizations/v1/model/create_resource_account_request.py
huaweicloudsdkorganizations/v1/model/create_resource_account_response.py
huaweicloudsdkorganizations-3.1.184.dist-info/METADATA
huaweicloudsdkorganizations-3.1.184.dist-info/WHEEL
huaweicloudsdkorganizations-3.1.184.dist-info/licenses/LICENSE
huaweicloudsdkorganizations-3.1.184.dist-info/RECORD
